{"title":"axel F remix by DJ nerd","uid":5791469,"size":4490496,"categoryP":"audio","categoryS":"music","magnet":"?xt=urn:btih:0c650513dd7f388c124c2b7ac394358c34b26eda&amp;dn=axel+F+remix+by+DJ+nerd&amp;tr=udp%3A%2F%2Ftracker.openbittorrent.com%3A80&amp;tr=udp%3A%2F%2Fopen.demonii.com%3A1337&amp;tr=udp%3A%2F%2Ftracker.coppersurfer.tk%3A6969&amp;tr=udp%3A%2F%2Fexodus.desync.com%3A6969","seeders":0,"leechers":1,"uploader":"dragonheurt","files":1,"time":1282858803,"description":"axel F remixed  by DJnerd people where asking for download link so here it is","torrent":{"xt":"urn:btih:0c650513dd7f388c124c2b7ac394358c34b26eda","amp;dn":"axel+F+remix+by+DJ+nerd","amp;tr":["udp%3A%2F%2Ftracker.openbittorrent.com%3A80","udp%3A%2F%2Fopen.demonii.com%3A1337","udp%3A%2F%2Ftracker.coppersurfer.tk%3A6969","udp%3A%2F%2Fexodus.desync.com%3A6969"],"infoHash":"0c650513dd7f388c124c2b7ac394358c34b26eda","infoHashBuffer":{"type":"Buffer","data":[12,101,5,19,221,127,56,140,18,76,43,122,195,148,53,140,52,178,110,218]},"announce":[],"urlList":[]}}