{"title":"Knight and Day (2010) DVD NLT-Release","uid":5840045,"size":4129914316,"categoryP":"video","categoryS":"movies_dvdr","magnet":"?xt=urn:btih:0dcde0b0a8f4c70491433cffa67acbd408b28bce&amp;dn=Knight+and+Day+%282010%29+DVD+NLT-Release&amp;tr=udp%3A%2F%2Ftracker.openbittorrent.com%3A80&amp;tr=udp%3A%2F%2Fopen.demonii.com%3A1337&amp;tr=udp%3A%2F%2Ftracker.coppersurfer.tk%3A6969&amp;tr=udp%3A%2F%2Fexodus.desync.com%3A6969","seeders":0,"leechers":0,"uploader":"Nlt-Release-XX-Men","files":-1,"time":1284909271,"description":"Knight and Day (2010) DVD NLT-Release\n\n\n[url=http://www.moviemeter.nl/film/62358]Moviemeter[/url]\nVanaf 15 juli in de bioscoop\nVerenigde Staten\nActie / Komedie\n110 minuten\ngeregisseerd door James Mangold\nmet Tom Cruise, Cameron Diaz en Maggie Grace\n\n'Knight and Day' gaat over de eenzame vrouw June (Cameron Diaz), wier ogenschijnlijk onschuldige blind date haar leven op zijn kop zet. De blind date, een superspion genaamd Milner (Tom Cruise), neemt haar mee op een gewelddadige wereldreis om een batterij te beschermen die de sleutel bevat tot een oneindige krachtbron.\nVanaf 15 juli in de bioscoop\n==========================================\n[url=http://www.imdb.com/title/tt1013743/]IMDB[/url]\nAs of July 15 in the cinema\nUnited States\nAction / Comedy\n110 minutes\ndirected by James Mangold\nTom Cruise, Cameron Diaz and Maggie Grace\n\n&quot;Knight and Day 'is about a lonely wife June (Cameron Diaz), whose seemingly innocent blind date her life upside down. The blind date, a super spy named Milner (Tom Cruise) takes her to a violent world to protect a battery contains the key to infinite power.\n\n==========================================\nMovie..............: Knight and Day (2010) \ngenre..............: Aktie / Komedie\nSource.............: DVD9-ELEKTRI4KA / Knight and Day (2010)R5 DVD9 \nFormat.............: DVDR\nruntime............: 110 min.\nMenu...............: Nope.\nVideo..............: Untouched\nAudio..............: SOURCE AUDIO =R5 LINE AC3 -PrisMCodec:::::::::::::::: AC3\nBitrate:::::::::::::: 448\nFrequency:::::::::::: 48.0Khz\nAudio Source::::::::: Lap And Russian AC3 Thanks to both 5.1 -iNK Eng: DD 5.1\nSubtitles..........: Vertaald door Tokke, Biteme &amp; Suurtje, Klasse vertaling weer geheel op audio!!\nControle...........: Suurtje\nBewerking+Resync...: Suurtje \nUser Rating:IMDb (6,7 / 2901) \nSpotinformatie \nCategorie : Beeld \nFormaat : DVD5 \nBron : R5\n \nOndertitels : Nederlands (instelbaar)\n \nGenre : Actie Komedie\n \n\nEnjoy the movie\n\nXX-Men","torrent":{"xt":"urn:btih:0dcde0b0a8f4c70491433cffa67acbd408b28bce","amp;dn":"Knight+and+Day+%282010%29+DVD+NLT-Release","amp;tr":["udp%3A%2F%2Ftracker.openbittorrent.com%3A80","udp%3A%2F%2Fopen.demonii.com%3A1337","udp%3A%2F%2Ftracker.coppersurfer.tk%3A6969","udp%3A%2F%2Fexodus.desync.com%3A6969"],"infoHash":"0dcde0b0a8f4c70491433cffa67acbd408b28bce","infoHashBuffer":{"type":"Buffer","data":[13,205,224,176,168,244,199,4,145,67,60,255,166,122,203,212,8,178,139,206]},"announce":[],"urlList":[]}}