{"title":"[720p] BlowJob Fridays - Lynn Love - The Cock Lover","uid":5850864,"size":541139969,"categoryP":"porn","categoryS":"hd___movies","magnet":"?xt=urn:btih:1ac667538dddca88bc14af42bc14a364971d4f23&amp;dn=%5B720p%5D+BlowJob+Fridays+-+Lynn+Love+-+The+Cock+Lover&amp;tr=udp%3A%2F%2Ftracker.openbittorrent.com%3A80&amp;tr=udp%3A%2F%2Fopen.demonii.com%3A1337&amp;tr=udp%3A%2F%2Ftracker.coppersurfer.tk%3A6969&amp;tr=udp%3A%2F%2Fexodus.desync.com%3A6969","seeders":0,"leechers":0,"uploader":"beta2008x","files":1,"time":1285378770,"description":" &lt;a href=&quot;http://www.dumppix.com/viewer.php?file=7wohm_BlowJob_Fridays_1.jpg&quot; rel=&quot;nofollow&quot; target=&quot;_NEW&quot;&gt;http://www.dumppix.com/viewer.php?file=7wohm_BlowJob_Fridays_1.jpg&lt;/a&gt;\n &lt;a href=&quot;\nhttp://www.dumppix.com/viewer.php?file=7evw0_BlowJob_Fridays_2.jpg&quot; rel=&quot;nofollow&quot; target=&quot;_NEW&quot;&gt;\nhttp://www.dumppix.com/viewer.php?file=7evw0_BlowJob_Fridays_2.jpg&lt;/a&gt;\n &lt;a href=&quot;\nhttp://www.dumppix.com/viewer.php?file=3tb0_BlowJob_Fridays_3.jpg&quot; rel=&quot;nofollow&quot; target=&quot;_NEW&quot;&gt;\nhttp://www.dumppix.com/viewer.php?file=3tb0_BlowJob_Fridays_3.jpg&lt;/a&gt;\n &lt;a href=&quot;\nhttp://www.dumppix.com/viewer.php?file=rfidg_BlowJob_Fridays_4.jpg&quot; rel=&quot;nofollow&quot; target=&quot;_NEW&quot;&gt;\nhttp://www.dumppix.com/viewer.php?file=rfidg_BlowJob_Fridays_4.jpg&lt;/a&gt;\n &lt;a href=&quot;\nhttp://www.dumppix.com/viewer.php?file=qba48_BlowJob_Fridays_5.jpg&quot; rel=&quot;nofollow&quot; target=&quot;_NEW&quot;&gt;\nhttp://www.dumppix.com/viewer.php?file=qba48_BlowJob_Fridays_5.jpg&lt;/a&gt;\n &lt;a href=&quot;\nhttp://www.dumppix.com/viewer.php?file=0nau2_BlowJob_Fridays_6.jpg&quot; rel=&quot;nofollow&quot; target=&quot;_NEW&quot;&gt;\nhttp://www.dumppix.com/viewer.php?file=0nau2_BlowJob_Fridays_6.jpg&lt;/a&gt;\n &lt;a href=&quot;\nhttp://www.dumppix.com/viewer.php?file=bdc7f_bj7258_3000_preview.jpg&quot; rel=&quot;nofollow&quot; target=&quot;_NEW&quot;&gt;\nhttp://www.dumppix.com/viewer.php?file=bdc7f_bj7258_3000_preview.jpg&lt;/a&gt;\n\n\nBlowJob Fridays - Lynn Love - The Cock Lover\n\nAdded: Friday, September 24, 2010  \n\nLength: 20 minutes  \nAh shit! It's about that time. It's Blow Job Fridays bitches! We got a special treat for you. She goes by the name of Lynn Love. What a sexy piece of ass! She's here to give an awesome blow-job for today's new update. Max Cartel is one lucky fucker. Having your cock sucked by a dime piece is every man's dream. Lynn Love sucked Max's cock just the way it's suppose to be done. Cum and see. Enjoy!\t  \t\n\nGirls: Lynn Love ","torrent":{"xt":"urn:btih:1ac667538dddca88bc14af42bc14a364971d4f23","amp;dn":"%5B720p%5D+BlowJob+Fridays+-+Lynn+Love+-+The+Cock+Lover","amp;tr":["udp%3A%2F%2Ftracker.openbittorrent.com%3A80","udp%3A%2F%2Fopen.demonii.com%3A1337","udp%3A%2F%2Ftracker.coppersurfer.tk%3A6969","udp%3A%2F%2Fexodus.desync.com%3A6969"],"infoHash":"1ac667538dddca88bc14af42bc14a364971d4f23","infoHashBuffer":{"type":"Buffer","data":[26,198,103,83,141,221,202,136,188,20,175,66,188,20,163,100,151,29,79,35]},"announce":[],"urlList":[]}}