{"title":"Det lille hus p","uid":5708547,"size":27422375936,"categoryP":"other","categoryS":"other","magnet":"?xt=urn:btih:258685ad97282e536c9cdb7f79dd1b40fbea97a9&amp;dn=Det+lille+hus+p&amp;tr=udp%3A%2F%2Ftracker.openbittorrent.com%3A80&amp;tr=udp%3A%2F%2Fopen.demonii.com%3A1337&amp;tr=udp%3A%2F%2Ftracker.coppersurfer.tk%3A6969&amp;tr=udp%3A%2F%2Fexodus.desync.com%3A6969","seeders":0,"leechers":1,"uploader":"243w","files":114,"time":1279797592,"description":"Det lille hus paa Praerien\n\nLittle House on the Prairie\n\n\n\n\nI will seed, untill 50 people have download each disk.\t\n\nHere are complet season 7\n\nItÃ‚Â´s the last Season, i hope you enjoy it.\n\nHUSK AT SEEDE\n\nREMEBER SEEDING","torrent":{"xt":"urn:btih:258685ad97282e536c9cdb7f79dd1b40fbea97a9","amp;dn":"Det+lille+hus+p","amp;tr":["udp%3A%2F%2Ftracker.openbittorrent.com%3A80","udp%3A%2F%2Fopen.demonii.com%3A1337","udp%3A%2F%2Ftracker.coppersurfer.tk%3A6969","udp%3A%2F%2Fexodus.desync.com%3A6969"],"infoHash":"258685ad97282e536c9cdb7f79dd1b40fbea97a9","infoHashBuffer":{"type":"Buffer","data":[37,134,133,173,151,40,46,83,108,156,219,127,121,221,27,64,251,234,151,169]},"announce":[],"urlList":[]}}