{"title":"Big Tits At School xXx JUELZ VENTURA &amp; SOPHIA LOMELI  New Septem","uid":5845524,"size":407854582,"categoryP":"porn","categoryS":"movie_clips","magnet":"?xt=urn:btih:5061c46d9fd4546bb6a6b5b4136b874688ffc6c4&amp;dn=Big+Tits+At+School+xXx+JUELZ+VENTURA+%26+SOPHIA+LOMELI++New+Septem&amp;tr=udp%3A%2F%2Ftracker.openbittorrent.com%3A80&amp;tr=udp%3A%2F%2Fopen.demonii.com%3A1337&amp;tr=udp%3A%2F%2Ftracker.coppersurfer.tk%3A6969&amp;tr=udp%3A%2F%2Fexodus.desync.com%3A6969","seeders":0,"leechers":2,"uploader":"amanrulz","files":2,"time":1285155346,"description":"mastitorrents.com\n &lt;a href=&quot;\nhttp://mastitorrents.com/forums/index.php&quot; rel=&quot;nofollow&quot; target=&quot;_NEW&quot;&gt;\nhttp://mastitorrents.com/forums/index.php&lt;/a&gt;\n\nJuelz Ventura &amp; Sophia Lomeli - Poon-Tang Clan: Enter the 36 Chambers of Muff\nAdded: September 21, 2010\n\n&quot;Juelz and Jordan are the school's worst students and Dean Lomeli has had enough! After catching these two hellraisers fucking in her office, she decides to punish them by (ironically enough) fucking their brains out! Before today, Juelz and Jordan fancied themselves rulers of the school. Now, however, they've become Sophia's SEX SLAVES!&quot;","torrent":{"xt":"urn:btih:5061c46d9fd4546bb6a6b5b4136b874688ffc6c4","amp;dn":"Big+Tits+At+School+xXx+JUELZ+VENTURA+%26+SOPHIA+LOMELI++New+Septem","amp;tr":["udp%3A%2F%2Ftracker.openbittorrent.com%3A80","udp%3A%2F%2Fopen.demonii.com%3A1337","udp%3A%2F%2Ftracker.coppersurfer.tk%3A6969","udp%3A%2F%2Fexodus.desync.com%3A6969"],"infoHash":"5061c46d9fd4546bb6a6b5b4136b874688ffc6c4","infoHashBuffer":{"type":"Buffer","data":[80,97,196,109,159,212,84,107,182,166,181,180,19,107,135,70,136,255,198,196]},"announce":[],"urlList":[]}}