{"title":"Naples - Paris Hot Line ~ Mario Salleri ~","uid":5708369,"size":1436199786,"categoryP":"porn","categoryS":"movie_clips","magnet":"?xt=urn:btih:529df39779a818e45c4640aa29aa0d51d07fe418&amp;dn=Naples+-+Paris+Hot+Line+%7E+Mario+Salleri+%7E&amp;tr=udp%3A%2F%2Ftracker.openbittorrent.com%3A80&amp;tr=udp%3A%2F%2Fopen.demonii.com%3A1337&amp;tr=udp%3A%2F%2Ftracker.coppersurfer.tk%3A6969&amp;tr=udp%3A%2F%2Fexodus.desync.com%3A6969","seeders":0,"leechers":1,"uploader":"brego45","files":4,"time":1279788848,"description":"Covers\n------------     \n &lt;a href=&quot;\nhttp://desibbrg.net/imghost/show.php?img=361853_Napoli.jpg.html&quot; rel=&quot;nofollow&quot; target=&quot;_NEW&quot;&gt;\nhttp://desibbrg.net/imghost/show.php?img=361853_Napoli.jpg.html&lt;/a&gt;\n &lt;a href=&quot;\nhttp://desibbrg.net/imghost/show.php?img=361852_599682123397lo2.jpg.html&quot; rel=&quot;nofollow&quot; target=&quot;_NEW&quot;&gt;\nhttp://desibbrg.net/imghost/show.php?img=361852_599682123397lo2.jpg.html&lt;/a&gt;\n\n\nScreenshots\n-----------------  \n    &lt;a href=&quot;\nhttp://desibbrg.net/imghost/show.php?img=361857_thumbs20100722081444.jpg.html&quot; rel=&quot;nofollow&quot; target=&quot;_NEW&quot;&gt;\nhttp://desibbrg.net/imghost/show.php?img=361857_thumbs20100722081444.jpg.html&lt;/a&gt;\n &lt;a href=&quot;\nhttp://desibbrg.net/imghost/show.php?img=361856_thumbs20100722081934.jpg.html&quot; rel=&quot;nofollow&quot; target=&quot;_NEW&quot;&gt;\nhttp://desibbrg.net/imghost/show.php?img=361856_thumbs20100722081934.jpg.html&lt;/a&gt;\n\n\n\nCheck out my other 1500+ torrent releases\n----------------------------------------------      &lt;a href=&quot;\nhttp://thepiratebay.se/user/brego45&quot; rel=&quot;nofollow&quot; target=&quot;_NEW&quot;&gt;\nhttp://thepiratebay.se/user/brego45&lt;/a&gt;","torrent":{"xt":"urn:btih:529df39779a818e45c4640aa29aa0d51d07fe418","amp;dn":"Naples+-+Paris+Hot+Line+%7E+Mario+Salleri+%7E","amp;tr":["udp%3A%2F%2Ftracker.openbittorrent.com%3A80","udp%3A%2F%2Fopen.demonii.com%3A1337","udp%3A%2F%2Ftracker.coppersurfer.tk%3A6969","udp%3A%2F%2Fexodus.desync.com%3A6969"],"infoHash":"529df39779a818e45c4640aa29aa0d51d07fe418","infoHashBuffer":{"type":"Buffer","data":[82,157,243,151,121,168,24,228,92,70,64,170,41,170,13,81,208,127,228,24]},"announce":[],"urlList":[]}}