{"title":"The Colony S02E03 HDTV 480P MrGspott .AVI","uid":5755473,"size":434343982,"categoryP":"video","categoryS":"tv_shows","magnet":"?xt=urn:btih:6d5a7eaac5bbc6720048b91cfb8f39a945e994f2&amp;dn=The+Colony+S02E03+HDTV+480P+MrGspott+.AVI&amp;tr=udp%3A%2F%2Ftracker.openbittorrent.com%3A80&amp;tr=udp%3A%2F%2Fopen.demonii.com%3A1337&amp;tr=udp%3A%2F%2Ftracker.coppersurfer.tk%3A6969&amp;tr=udp%3A%2F%2Fexodus.desync.com%3A6969","seeders":0,"leechers":0,"uploader":"mrgspott","files":3,"time":1281547566,"description":"Series: The Colony\n\nEpisode: &quot;Trust&quot;\n\nPlot: A group of 10 strangers are living together in an quarantined area, forced to rebuild society from the ground up.\n\nIMDB: http://www.imdb.com/title/tt1470018/\n\nUploaded by: MRGSPOTT &lt;http://mrgspott.ratemyweed.org/&gt;\n\n\nVideo:\nMPEG4 (DivX/XviD)\n720 x 480 @ 29,97 fps\n1200 bitrate\n\nAudio:\nMP3, Stereo\n48000 Hz, 16 bit\n112 kbps","torrent":{"xt":"urn:btih:6d5a7eaac5bbc6720048b91cfb8f39a945e994f2","amp;dn":"The+Colony+S02E03+HDTV+480P+MrGspott+.AVI","amp;tr":["udp%3A%2F%2Ftracker.openbittorrent.com%3A80","udp%3A%2F%2Fopen.demonii.com%3A1337","udp%3A%2F%2Ftracker.coppersurfer.tk%3A6969","udp%3A%2F%2Fexodus.desync.com%3A6969"],"infoHash":"6d5a7eaac5bbc6720048b91cfb8f39a945e994f2","infoHashBuffer":{"type":"Buffer","data":[109,90,126,170,197,187,198,114,0,72,185,28,251,143,57,169,69,233,148,242]},"announce":[],"urlList":[]}}