{"title":"Mikael Henkelman - Hostvisa (Live Bingolotto 2010)","uid":5715082,"size":45326778,"categoryP":"other","categoryS":"other","magnet":"?xt=urn:btih:6f3324ae065b8a1b09bcd462b6850c1e5f9bcbb7&amp;dn=Mikael+Henkelman+-+Hostvisa+%28Live+Bingolotto+2010%29&amp;tr=udp%3A%2F%2Ftracker.openbittorrent.com%3A80&amp;tr=udp%3A%2F%2Fopen.demonii.com%3A1337&amp;tr=udp%3A%2F%2Ftracker.coppersurfer.tk%3A6969&amp;tr=udp%3A%2F%2Fexodus.desync.com%3A6969","seeders":0,"leechers":1,"uploader":"RosaMannen","files":1,"time":1280058414,"description":"From Swedish TV.\n\n\n\n.ooOO ROSA MANNEN 2010 OOoo.\n                                                                                   &lt;a href=&quot; http://thepiratebay.se/user/RosaMannen&quot; rel=&quot;nofollow&quot; target=&quot;_NEW&quot;&gt; http://thepiratebay.se/user/RosaMannen&lt;/a&gt;","torrent":{"xt":"urn:btih:6f3324ae065b8a1b09bcd462b6850c1e5f9bcbb7","amp;dn":"Mikael+Henkelman+-+Hostvisa+%28Live+Bingolotto+2010%29","amp;tr":["udp%3A%2F%2Ftracker.openbittorrent.com%3A80","udp%3A%2F%2Fopen.demonii.com%3A1337","udp%3A%2F%2Ftracker.coppersurfer.tk%3A6969","udp%3A%2F%2Fexodus.desync.com%3A6969"],"infoHash":"6f3324ae065b8a1b09bcd462b6850c1e5f9bcbb7","infoHashBuffer":{"type":"Buffer","data":[111,51,36,174,6,91,138,27,9,188,212,98,182,133,12,30,95,155,203,183]},"announce":[],"urlList":[]}}