{"title":"Neal Boortz Show - Tuesday, November 2, 2010 MP3 not CF","uid":5930108,"size":44641676,"categoryP":"audio","categoryS":"other","magnet":"?xt=urn:btih:7329c5645ebf5c22a95317215d457d538f2084aa&amp;dn=Neal+Boortz+Show+-+Tuesday%2C+November+2%2C+2010+MP3+not+CF&amp;tr=udp%3A%2F%2Ftracker.openbittorrent.com%3A80&amp;tr=udp%3A%2F%2Fopen.demonii.com%3A1337&amp;tr=udp%3A%2F%2Ftracker.coppersurfer.tk%3A6969&amp;tr=udp%3A%2F%2Fexodus.desync.com%3A6969","seeders":0,"leechers":0,"uploader":"amuck5","files":4,"time":1288745165,"description":"Neal Boortz Show - Tuesday, November 2, 2010 MP3 not CF","torrent":{"xt":"urn:btih:7329c5645ebf5c22a95317215d457d538f2084aa","amp;dn":"Neal+Boortz+Show+-+Tuesday%2C+November+2%2C+2010+MP3+not+CF","amp;tr":["udp%3A%2F%2Ftracker.openbittorrent.com%3A80","udp%3A%2F%2Fopen.demonii.com%3A1337","udp%3A%2F%2Ftracker.coppersurfer.tk%3A6969","udp%3A%2F%2Fexodus.desync.com%3A6969"],"infoHash":"7329c5645ebf5c22a95317215d457d538f2084aa","infoHashBuffer":{"type":"Buffer","data":[115,41,197,100,94,191,92,34,169,83,23,33,93,69,125,83,143,32,132,170]},"announce":[],"urlList":[]}}