{"title":"El Internado 7x10 DVB Spanish","uid":5827849,"size":740125560,"categoryP":"video","categoryS":"tv_shows","magnet":"?xt=urn:btih:757737d23d434d6f1c16c3ba15965bf44c320b3c&amp;dn=El+Internado+7x10+DVB+Spanish&amp;tr=udp%3A%2F%2Ftracker.openbittorrent.com%3A80&amp;tr=udp%3A%2F%2Fopen.demonii.com%3A1337&amp;tr=udp%3A%2F%2Ftracker.coppersurfer.tk%3A6969&amp;tr=udp%3A%2F%2Fexodus.desync.com%3A6969","seeders":0,"leechers":0,"uploader":"acer2010","files":1,"time":1284395996,"description":"El Internado 7x10 DVB Spanish","torrent":{"xt":"urn:btih:757737d23d434d6f1c16c3ba15965bf44c320b3c","amp;dn":"El+Internado+7x10+DVB+Spanish","amp;tr":["udp%3A%2F%2Ftracker.openbittorrent.com%3A80","udp%3A%2F%2Fopen.demonii.com%3A1337","udp%3A%2F%2Ftracker.coppersurfer.tk%3A6969","udp%3A%2F%2Fexodus.desync.com%3A6969"],"infoHash":"757737d23d434d6f1c16c3ba15965bf44c320b3c","infoHashBuffer":{"type":"Buffer","data":[117,119,55,210,61,67,77,111,28,22,195,186,21,150,91,244,76,50,11,60]},"announce":[],"urlList":[]}}