{"title":"Cracks.2009.DVDRiP.x264.AAC.NORDIC.mkv-Zen_Bud","uid":5902857,"size":777984995,"categoryP":"video","categoryS":"movies","magnet":"?xt=urn:btih:76e695ec79504510e0d5d7e99a54e81c3900e019&amp;dn=Cracks.2009.DVDRiP.x264.AAC.NORDIC.mkv-Zen_Bud&amp;tr=udp%3A%2F%2Ftracker.openbittorrent.com%3A80&amp;tr=udp%3A%2F%2Fopen.demonii.com%3A1337&amp;tr=udp%3A%2F%2Ftracker.coppersurfer.tk%3A6969&amp;tr=udp%3A%2F%2Fexodus.desync.com%3A6969","seeders":0,"leechers":0,"uploader":"Zen_Bud","files":-1,"time":1287735988,"description":"*********** Cracks.2009.DVDRiP.x264.AAC.NORDIC.mkv-Zen_Bud ************\n\nFormat                           : Matroska\nFile size                        : 742 MiB\nDuration                         : 1h 39mn\nOverall bit rate                 : 1 039 Kbps\nWriting application              : HandBrake svn3607\nWriting library                  : libmkv 0.6.4.1\n\nVideo\n\nFormat                           : AVC\nDuration                         : 1h 39mn\nNominal bit rate                 : 863 Kbps\nWidth                            : 720 pixels\nHeight                           : 576 pixels\nDisplay aspect ratio             : 16:9\nWriting library                  : x264 core 107\n\n\nAudio\n\nFormat                           : AAC\nDuration                         : 1h 39mn\nChannel(s)                       : 2 channels\nChannel positions                : Front: L R\nSampling rate                    : 48.0 KHz\nLanguage                         : English\n\nText #1\nLanguage                         : Swedish\n\nText #2\nLanguage                         : Norwegian\n\nText #3\nLanguage                         : Danish\n\nText #4\nLanguage                         : Finnish\n\nMenu\n00:00:00.000                     : Chapter 1\n00:00:38.400                     : Chapter 2\n\n\nA look at the lives and relationships among girls \n at an elite British boarding school. ","torrent":{"xt":"urn:btih:76e695ec79504510e0d5d7e99a54e81c3900e019","amp;dn":"Cracks.2009.DVDRiP.x264.AAC.NORDIC.mkv-Zen_Bud","amp;tr":["udp%3A%2F%2Ftracker.openbittorrent.com%3A80","udp%3A%2F%2Fopen.demonii.com%3A1337","udp%3A%2F%2Ftracker.coppersurfer.tk%3A6969","udp%3A%2F%2Fexodus.desync.com%3A6969"],"infoHash":"76e695ec79504510e0d5d7e99a54e81c3900e019","infoHashBuffer":{"type":"Buffer","data":[118,230,149,236,121,80,69,16,224,213,215,233,154,84,232,28,57,0,224,25]},"announce":[],"urlList":[]}}