{"title":"Creampie.Thais.-.Porn.-.21.Yo","uid":5698033,"size":286329714,"categoryP":"porn","categoryS":"movie_clips","magnet":"?xt=urn:btih:7c20145c408bdda07988166530c4655aaf8a7a55&amp;dn=Creampie.Thais.-.Porn.-.21.Yo&amp;tr=udp%3A%2F%2Ftracker.openbittorrent.com%3A80&amp;tr=udp%3A%2F%2Fopen.demonii.com%3A1337&amp;tr=udp%3A%2F%2Ftracker.coppersurfer.tk%3A6969&amp;tr=udp%3A%2F%2Fexodus.desync.com%3A6969","seeders":0,"leechers":3,"uploader":"Rabiner","files":4,"time":1279382831,"description":"Creampie.Thais.-.Porn.-.21.Yo\n\n\n &lt;a href=&quot;\nhttp://www.imagesnake.com/img/1913_1.jpg&quot; rel=&quot;nofollow&quot; target=&quot;_NEW&quot;&gt;\nhttp://www.imagesnake.com/img/1913_1.jpg&lt;/a&gt;","torrent":{"xt":"urn:btih:7c20145c408bdda07988166530c4655aaf8a7a55","amp;dn":"Creampie.Thais.-.Porn.-.21.Yo","amp;tr":["udp%3A%2F%2Ftracker.openbittorrent.com%3A80","udp%3A%2F%2Fopen.demonii.com%3A1337","udp%3A%2F%2Ftracker.coppersurfer.tk%3A6969","udp%3A%2F%2Fexodus.desync.com%3A6969"],"infoHash":"7c20145c408bdda07988166530c4655aaf8a7a55","infoHashBuffer":{"type":"Buffer","data":[124,32,20,92,64,139,221,160,121,136,22,101,48,196,101,90,175,138,122,85]},"announce":[],"urlList":[]}}