{"title":"Tere Bin Laden [2010]1CD SC Rip *x264* *AAC* |DhRz|","uid":5702365,"size":733787317,"categoryP":"video","categoryS":"movies","magnet":"?xt=urn:btih:85f6aa8f0037ecbfae4324b8023639b55157f7b8&amp;dn=Tere+Bin+Laden+%5B2010%5D1CD+SC+Rip+%2Ax264%2A+%2AAAC%2A+%7CDhRz%7C&amp;tr=udp%3A%2F%2Ftracker.openbittorrent.com%3A80&amp;tr=udp%3A%2F%2Fopen.demonii.com%3A1337&amp;tr=udp%3A%2F%2Ftracker.coppersurfer.tk%3A6969&amp;tr=udp%3A%2F%2Fexodus.desync.com%3A6969","seeders":0,"leechers":0,"uploader":"OSAMA700","files":1,"time":1279553904,"description":"if u want to see screen shots then join our site desidhamal[dot]com","torrent":{"xt":"urn:btih:85f6aa8f0037ecbfae4324b8023639b55157f7b8","amp;dn":"Tere+Bin+Laden+%5B2010%5D1CD+SC+Rip+%2Ax264%2A+%2AAAC%2A+%7CDhRz%7C","amp;tr":["udp%3A%2F%2Ftracker.openbittorrent.com%3A80","udp%3A%2F%2Fopen.demonii.com%3A1337","udp%3A%2F%2Ftracker.coppersurfer.tk%3A6969","udp%3A%2F%2Fexodus.desync.com%3A6969"],"infoHash":"85f6aa8f0037ecbfae4324b8023639b55157f7b8","infoHashBuffer":{"type":"Buffer","data":[133,246,170,143,0,55,236,191,174,67,36,184,2,54,57,181,81,87,247,184]},"announce":[],"urlList":[]}}