{"title":"Halo Reach Game Theme:Windows 7[Orion_Me]","uid":5845755,"size":11664075,"categoryP":"other","categoryS":"other","magnet":"?xt=urn:btih:90bffb35a69439bed8ca2862933294d0366added&amp;dn=Halo+Reach+Game+Theme%3AWindows+7%5BOrion_Me%5D&amp;tr=udp%3A%2F%2Ftracker.openbittorrent.com%3A80&amp;tr=udp%3A%2F%2Fopen.demonii.com%3A1337&amp;tr=udp%3A%2F%2Ftracker.coppersurfer.tk%3A6969&amp;tr=udp%3A%2F%2Fexodus.desync.com%3A6969","seeders":0,"leechers":0,"uploader":"Orion_Me","files":-1,"time":1285168825,"description":"_____________________________________________________________________________ \n       ooooooo        ooooooo       ooo       ooooooo      ooooo      ooo\n    ooo       ooo  ooo       ooo    ooo    ooo       ooo   oooooo     ooo \n    ooo       ooo  ooo      ooo     ooo    ooo       ooo   ooo ooo    ooo \n    ooo       ooo  ooo     ooo      ooo    ooo       ooo   ooo  ooo   ooo \n    ooo       ooo  oooooooooo       ooo    ooo       ooo   ooo   ooo  ooo\n    ooo       ooo  ooo     ooo      ooo    ooo       ooo   ooo    ooo ooo\n    ooo       ooo  ooo      ooo     ooo    ooo       ooo   ooo     oooooo\n       ooooooo     ooo       ooo    ooo       ooooooo      ooo      ooooo\n          \n                                                 \n                        ooooooo ooooooo         ooooooo       \n                      ooo     ooo     ooo     ooo\n                      ooo     ooo     ooo     ooo\n                      ooo     ooo     ooo     ooooooooo\n                      ooo     ooo     ooo     ooooooooo\n                      ooo     ooo     ooo     ooo\n                      ooo     ooo     ooo     ooo\n                      ooo     ooo     ooo       ooooooo\n______________________________________________________________________________\n\nThe theme is for Windows 7.This is NOT a WindowBlinds theme but a simple theme which consists of complete custom sounds,Hi-Res wallpapers and desktop icons.Thanks to all those who have and continue to help me seeding.Do comment and say thanks/rate up/vote if you like it\n\nScreens: &lt;a href=&quot;\nhttp://img838.imageshack.us/img838/3811/haloreachiconsvikitech.jpg&quot; rel=&quot;nofollow&quot; target=&quot;_NEW&quot;&gt;\nhttp://img838.imageshack.us/img838/3811/haloreachiconsvikitech.jpg&lt;/a&gt; &lt;a href=&quot;\nhttp://img198.imageshack.us/img198/8421/haloreachthemevikitech.png&quot; rel=&quot;nofollow&quot; target=&quot;_NEW&quot;&gt;\nhttp://img198.imageshack.us/img198/8421/haloreachthemevikitech.png&lt;/a&gt; &lt;a href=&quot;\nhttp://img163.imageshack.us/img163/9530/haloreachwallpaper02vik.jpg&quot; rel=&quot;nofollow&quot; target=&quot;_NEW&quot;&gt;\nhttp://img163.imageshack.us/img163/9530/haloreachwallpaper02vik.jpg&lt;/a&gt; &lt;a href=&quot;\nhttp://img833.imageshack.us/img833/6174/haloreachwallpaper04vik.jpg&quot; rel=&quot;nofollow&quot; target=&quot;_NEW&quot;&gt;\nhttp://img833.imageshack.us/img833/6174/haloreachwallpaper04vik.jpg&lt;/a&gt; &lt;a href=&quot;\nhttp://img718.imageshack.us/img718/9021/haloreachwallpaper05vik.jpg&quot; rel=&quot;nofollow&quot; target=&quot;_NEW&quot;&gt;\nhttp://img718.imageshack.us/img718/9021/haloreachwallpaper05vik.jpg&lt;/a&gt; &lt;a href=&quot;\nhttp://img541.imageshack.us/img541/729/haloreachwallpaper06vik.jpg&quot; rel=&quot;nofollow&quot; target=&quot;_NEW&quot;&gt;\nhttp://img541.imageshack.us/img541/729/haloreachwallpaper06vik.jpg&lt;/a&gt; &lt;a href=&quot;\nhttp://img201.imageshack.us/img201/4895/haloreachwallpaper07vik.jpg&quot; rel=&quot;nofollow&quot; target=&quot;_NEW&quot;&gt;\nhttp://img201.imageshack.us/img201/4895/haloreachwallpaper07vik.jpg&lt;/a&gt; &lt;a href=&quot;\nhttp://img822.imageshack.us/img822/6130/haloreachwallpaper09vik.jpg&quot; rel=&quot;nofollow&quot; target=&quot;_NEW&quot;&gt;\nhttp://img822.imageshack.us/img822/6130/haloreachwallpaper09vik.jpg&lt;/a&gt; &lt;a href=&quot;\nhttp://img199.imageshack.us/img199/7012/haloreachwallpaper10vik.jpg&quot; rel=&quot;nofollow&quot; target=&quot;_NEW&quot;&gt;\nhttp://img199.imageshack.us/img199/7012/haloreachwallpaper10vik.jpg&lt;/a&gt; &lt;a href=&quot;\nhttp://img121.imageshack.us/img121/1940/haloreachwallpaper11vik.jpg&quot; rel=&quot;nofollow&quot; target=&quot;_NEW&quot;&gt;\nhttp://img121.imageshack.us/img121/1940/haloreachwallpaper11vik.jpg&lt;/a&gt; &lt;a href=&quot;\nhttp://img411.imageshack.us/img411/8733/haloreachwallpaper12vik.jpg&quot; rel=&quot;nofollow&quot; target=&quot;_NEW&quot;&gt;\nhttp://img411.imageshack.us/img411/8733/haloreachwallpaper12vik.jpg&lt;/a&gt; &lt;a href=&quot;\nhttp://img22.imageshack.us/img22/3636/haloreachwallpaper16vik.jpg&quot; rel=&quot;nofollow&quot; target=&quot;_NEW&quot;&gt;\nhttp://img22.imageshack.us/img22/3636/haloreachwallpaper16vik.jpg&lt;/a&gt; &lt;a href=&quot;\nhttp://img243.imageshack.us/img243/7595/haloreachwallpaper17vik.jpg&quot; rel=&quot;nofollow&quot; target=&quot;_NEW&quot;&gt;\nhttp://img243.imageshack.us/img243/7595/haloreachwallpaper17vik.jpg&lt;/a&gt; &lt;a href=&quot;\nhttp://img97.imageshack.us/img97/1830/haloreachwallpaper19vik.jpg&quot; rel=&quot;nofollow&quot; target=&quot;_NEW&quot;&gt;\nhttp://img97.imageshack.us/img97/1830/haloreachwallpaper19vik.jpg&lt;/a&gt; &lt;a href=&quot;\nhttp://bayimg.com/pApfAAace&quot; rel=&quot;nofollow&quot; target=&quot;_NEW&quot;&gt;\nhttp://bayimg.com/pApfAAace&lt;/a&gt;\n\n","torrent":{"xt":"urn:btih:90bffb35a69439bed8ca2862933294d0366added","amp;dn":"Halo+Reach+Game+Theme%3AWindows+7%5BOrion_Me%5D","amp;tr":["udp%3A%2F%2Ftracker.openbittorrent.com%3A80","udp%3A%2F%2Fopen.demonii.com%3A1337","udp%3A%2F%2Ftracker.coppersurfer.tk%3A6969","udp%3A%2F%2Fexodus.desync.com%3A6969"],"infoHash":"90bffb35a69439bed8ca2862933294d0366added","infoHashBuffer":{"type":"Buffer","data":[144,191,251,53,166,148,57,190,216,202,40,98,147,50,148,208,54,106,221,237]},"announce":[],"urlList":[]}}