{"title":"Real.Wife.Stories.-.Nikki.Sexx","uid":5703672,"size":553200604,"categoryP":"porn","categoryS":"movies","magnet":"?xt=urn:btih:962b9399768a7684d8fa103606380150a6f65adc&amp;dn=Real.Wife.Stories.-.Nikki.Sexx&amp;tr=udp%3A%2F%2Ftracker.openbittorrent.com%3A80&amp;tr=udp%3A%2F%2Fopen.demonii.com%3A1337&amp;tr=udp%3A%2F%2Ftracker.coppersurfer.tk%3A6969&amp;tr=udp%3A%2F%2Fexodus.desync.com%3A6969","seeders":0,"leechers":1,"uploader":"exmnova","files":4,"time":1279603583,"description":"Real.Wife.Stories.-.Nikki.Sexx\n\n &lt;a href=&quot;\nhttp://www.picswan.com/img/share.php?id=F719_4C45123E&quot; rel=&quot;nofollow&quot; target=&quot;_NEW&quot;&gt;\nhttp://www.picswan.com/img/share.php?id=F719_4C45123E&lt;/a&gt;\n\n\nMore Info:\n\n\n &lt;a href=&quot;\nhttp://www.69bits.com/torrent/MILF/20620/Real.Wife.Stories.-.Nikki.Sexx.html&quot; rel=&quot;nofollow&quot; target=&quot;_NEW&quot;&gt;\nhttp://www.69bits.com/torrent/MILF/20620/Real.Wife.Stories.-.Nikki.Sexx.html&lt;/a&gt;","torrent":{"xt":"urn:btih:962b9399768a7684d8fa103606380150a6f65adc","amp;dn":"Real.Wife.Stories.-.Nikki.Sexx","amp;tr":["udp%3A%2F%2Ftracker.openbittorrent.com%3A80","udp%3A%2F%2Fopen.demonii.com%3A1337","udp%3A%2F%2Ftracker.coppersurfer.tk%3A6969","udp%3A%2F%2Fexodus.desync.com%3A6969"],"infoHash":"962b9399768a7684d8fa103606380150a6f65adc","infoHashBuffer":{"type":"Buffer","data":[150,43,147,153,118,138,118,132,216,250,16,54,6,56,1,80,166,246,90,220]},"announce":[],"urlList":[]}}