{"title":"Dio - Diamonds - The Best Of Dio[1992","uid":5698742,"size":157363435,"categoryP":"other","categoryS":"other","magnet":"?xt=urn:btih:a2fb9f7957f10f4e2a25bbd5ab42413727ece6b5&amp;dn=Dio+-+Diamonds+-+The+Best+Of+Dio%5B1992&amp;tr=udp%3A%2F%2Ftracker.openbittorrent.com%3A80&amp;tr=udp%3A%2F%2Fopen.demonii.com%3A1337&amp;tr=udp%3A%2F%2Ftracker.coppersurfer.tk%3A6969&amp;tr=udp%3A%2F%2Fexodus.desync.com%3A6969","seeders":0,"leechers":0,"uploader":null,"files":13,"time":1279411438,"description":"Dio - Diamonds - The Best Of Dio[1992] pl seed and make a comment","torrent":{"xt":"urn:btih:a2fb9f7957f10f4e2a25bbd5ab42413727ece6b5","amp;dn":"Dio+-+Diamonds+-+The+Best+Of+Dio%5B1992","amp;tr":["udp%3A%2F%2Ftracker.openbittorrent.com%3A80","udp%3A%2F%2Fopen.demonii.com%3A1337","udp%3A%2F%2Ftracker.coppersurfer.tk%3A6969","udp%3A%2F%2Fexodus.desync.com%3A6969"],"infoHash":"a2fb9f7957f10f4e2a25bbd5ab42413727ece6b5","infoHashBuffer":{"type":"Buffer","data":[162,251,159,121,87,241,15,78,42,37,187,213,171,66,65,55,39,236,230,181]},"announce":[],"urlList":[]}}