{"title":"WRC 2010 Round 07 Bulgaria Day 1 Highlights","uid":5685924,"size":391757301,"categoryP":"other","categoryS":"other","magnet":"?xt=urn:btih:a525efb45247678eaa8eec0b61084ac4b8d5ee29&amp;dn=WRC+2010+Round+07+Bulgaria+Day+1+Highlights&amp;tr=udp%3A%2F%2Ftracker.openbittorrent.com%3A80&amp;tr=udp%3A%2F%2Fopen.demonii.com%3A1337&amp;tr=udp%3A%2F%2Ftracker.coppersurfer.tk%3A6969&amp;tr=udp%3A%2F%2Fexodus.desync.com%3A6969","seeders":0,"leechers":0,"uploader":null,"files":2,"time":1278928972,"description":"## Genre:Rally\n\n## Year:2010\n\n## Duration:00:25:49  \n\n## Language: English\n\n## Location: Borovets, Bulgaria \n\n\n\n\n\n\n\n## Brief Description: These are the highlights of the first day of the 2010 Rally in Bulgaria.\n","torrent":{"xt":"urn:btih:a525efb45247678eaa8eec0b61084ac4b8d5ee29","amp;dn":"WRC+2010+Round+07+Bulgaria+Day+1+Highlights","amp;tr":["udp%3A%2F%2Ftracker.openbittorrent.com%3A80","udp%3A%2F%2Fopen.demonii.com%3A1337","udp%3A%2F%2Ftracker.coppersurfer.tk%3A6969","udp%3A%2F%2Fexodus.desync.com%3A6969"],"infoHash":"a525efb45247678eaa8eec0b61084ac4b8d5ee29","infoHashBuffer":{"type":"Buffer","data":[165,37,239,180,82,71,103,142,170,142,236,11,97,8,74,196,184,213,238,41]},"announce":[],"urlList":[]}}