{"title":"Ron Franklin - City Lights (2007)","uid":5790714,"size":62849138,"categoryP":"audio","categoryS":"music","magnet":"?xt=urn:btih:b6339e4b5219a9a4f58400f9cde5259d53146232&amp;dn=Ron+Franklin+-+City+Lights+%282007%29&amp;tr=udp%3A%2F%2Ftracker.openbittorrent.com%3A80&amp;tr=udp%3A%2F%2Fopen.demonii.com%3A1337&amp;tr=udp%3A%2F%2Ftracker.coppersurfer.tk%3A6969&amp;tr=udp%3A%2F%2Fexodus.desync.com%3A6969","seeders":0,"leechers":0,"uploader":"CanadaJoe","files":13,"time":1282838394,"description":" &lt;a href=&quot;\nhttp://www.allmusic.com/cg/amg.dll?p=amg&amp;sql=10:gcfoxqqrldse&quot; rel=&quot;nofollow&quot; target=&quot;_NEW&quot;&gt;\nhttp://www.allmusic.com/cg/amg.dll?p=amg&amp;sql=10:gcfoxqqrldse&lt;/a&gt;\n\nAlternative Country-Rock mp3@192kbps","torrent":{"xt":"urn:btih:b6339e4b5219a9a4f58400f9cde5259d53146232","amp;dn":"Ron+Franklin+-+City+Lights+%282007%29","amp;tr":["udp%3A%2F%2Ftracker.openbittorrent.com%3A80","udp%3A%2F%2Fopen.demonii.com%3A1337","udp%3A%2F%2Ftracker.coppersurfer.tk%3A6969","udp%3A%2F%2Fexodus.desync.com%3A6969"],"infoHash":"b6339e4b5219a9a4f58400f9cde5259d53146232","infoHashBuffer":{"type":"Buffer","data":[182,51,158,75,82,25,169,164,245,132,0,249,205,229,37,157,83,20,98,50]},"announce":[],"urlList":[]}}