{"title":"Hung.S01E07.720p.swesub.mp4","uid":5904822,"size":480813021,"categoryP":"video","categoryS":"hd___tv_shows","magnet":"?xt=urn:btih:c58b3f140f280ec0b0e0d8c1312545f1f97d0212&amp;dn=Hung.S01E07.720p.swesub.mp4&amp;tr=udp%3A%2F%2Ftracker.openbittorrent.com%3A80&amp;tr=udp%3A%2F%2Fopen.demonii.com%3A1337&amp;tr=udp%3A%2F%2Ftracker.coppersurfer.tk%3A6969&amp;tr=udp%3A%2F%2Fexodus.desync.com%3A6969","seeders":0,"leechers":0,"uploader":"ztmluno","files":1,"time":1287822978,"description":"Hung S01E07\n\nAudio: English\nHardcodedsubs: Swedish\n","torrent":{"xt":"urn:btih:c58b3f140f280ec0b0e0d8c1312545f1f97d0212","amp;dn":"Hung.S01E07.720p.swesub.mp4","amp;tr":["udp%3A%2F%2Ftracker.openbittorrent.com%3A80","udp%3A%2F%2Fopen.demonii.com%3A1337","udp%3A%2F%2Ftracker.coppersurfer.tk%3A6969","udp%3A%2F%2Fexodus.desync.com%3A6969"],"infoHash":"c58b3f140f280ec0b0e0d8c1312545f1f97d0212","infoHashBuffer":{"type":"Buffer","data":[197,139,63,20,15,40,14,192,176,224,216,193,49,37,69,241,249,125,2,18]},"announce":[],"urlList":[]}}