{"title":"Ultimo Aviso 2x06 2x07 HDTV DVB Spanish","uid":5839841,"size":1206638592,"categoryP":"video","categoryS":"tv_shows","magnet":"?xt=urn:btih:d4106dcbd0bdf5051868873a41d7dcec54f107c9&amp;dn=Ultimo+Aviso+2x06+2x07+HDTV+DVB+Spanish&amp;tr=udp%3A%2F%2Ftracker.openbittorrent.com%3A80&amp;tr=udp%3A%2F%2Fopen.demonii.com%3A1337&amp;tr=udp%3A%2F%2Ftracker.coppersurfer.tk%3A6969&amp;tr=udp%3A%2F%2Fexodus.desync.com%3A6969","seeders":0,"leechers":0,"uploader":"acer2010","files":2,"time":1284855908,"description":"Ultimo Aviso 2x06 2x07 HDTV DVB Spanish","torrent":{"xt":"urn:btih:d4106dcbd0bdf5051868873a41d7dcec54f107c9","amp;dn":"Ultimo+Aviso+2x06+2x07+HDTV+DVB+Spanish","amp;tr":["udp%3A%2F%2Ftracker.openbittorrent.com%3A80","udp%3A%2F%2Fopen.demonii.com%3A1337","udp%3A%2F%2Ftracker.coppersurfer.tk%3A6969","udp%3A%2F%2Fexodus.desync.com%3A6969"],"infoHash":"d4106dcbd0bdf5051868873a41d7dcec54f107c9","infoHashBuffer":{"type":"Buffer","data":[212,16,109,203,208,189,245,5,24,104,135,58,65,215,220,236,84,241,7,201]},"announce":[],"urlList":[]}}