{"title":"Thine - In Therapy (2002) [mp3@320]","uid":5722268,"size":136252452,"categoryP":"other","categoryS":"other","magnet":"?xt=urn:btih:dd29da35f953782135a3127b81441b78e1a01708&amp;dn=Thine+-+In+Therapy+%282002%29+%5Bmp3%40320%5D&amp;tr=udp%3A%2F%2Ftracker.openbittorrent.com%3A80&amp;tr=udp%3A%2F%2Fopen.demonii.com%3A1337&amp;tr=udp%3A%2F%2Ftracker.coppersurfer.tk%3A6969&amp;tr=udp%3A%2F%2Fexodus.desync.com%3A6969","seeders":0,"leechers":2,"uploader":"eifmspfjr","files":13,"time":1280324646,"description":"1. Best Kept Secret 05:36\n2. Feel 04:28\n3. In Therapy 04:04\n4. Homewrecker Extraordinaire 03:20\n5. Never Learn 05:00\n6. Contact Point 03:55\n7. In Red Rooms 04:10\n8. Last Better Day 05:05\n9. Deny Everything 04:22\n10. Bar 04:47\n11. Running 04:44\n12. Bleaker Audio 07:06\n\n\n &lt;a href=&quot;\nhttp://metal-archives.com/band.php?id=5840&amp;PHPSESSID=30bfe8c27b6e98b9b0a8ffe1e2adfade&quot; rel=&quot;nofollow&quot; target=&quot;_NEW&quot;&gt;\nhttp://metal-archives.com/band.php?id=5840&amp;PHPSESSID=30bfe8c27b6e98b9b0a8ffe1e2adfade&lt;/a&gt;","torrent":{"xt":"urn:btih:dd29da35f953782135a3127b81441b78e1a01708","amp;dn":"Thine+-+In+Therapy+%282002%29+%5Bmp3%40320%5D","amp;tr":["udp%3A%2F%2Ftracker.openbittorrent.com%3A80","udp%3A%2F%2Fopen.demonii.com%3A1337","udp%3A%2F%2Ftracker.coppersurfer.tk%3A6969","udp%3A%2F%2Fexodus.desync.com%3A6969"],"infoHash":"dd29da35f953782135a3127b81441b78e1a01708","infoHashBuffer":{"type":"Buffer","data":[221,41,218,53,249,83,120,33,53,163,18,123,129,68,27,120,225,160,23,8]},"announce":[],"urlList":[]}}