{"title":"TeenSexMovs.-.Berta.Aka.Grace","uid":5695201,"size":755849939,"categoryP":"porn","categoryS":"movie_clips","magnet":"?xt=urn:btih:fa1589fbbda8880bd05dfd262f6e1cc53f390b28&amp;dn=TeenSexMovs.-.Berta.Aka.Grace&amp;tr=udp%3A%2F%2Ftracker.openbittorrent.com%3A80&amp;tr=udp%3A%2F%2Fopen.demonii.com%3A1337&amp;tr=udp%3A%2F%2Ftracker.coppersurfer.tk%3A6969&amp;tr=udp%3A%2F%2Fexodus.desync.com%3A6969","seeders":0,"leechers":1,"uploader":"Rabiner","files":4,"time":1279279830,"description":"TeenSexMovs.-.Berta.Aka.Grace\n\n\n &lt;a href=&quot;\nhttp://www.imagesnake.com/img/1835_1.jpg&quot; rel=&quot;nofollow&quot; target=&quot;_NEW&quot;&gt;\nhttp://www.imagesnake.com/img/1835_1.jpg&lt;/a&gt;","torrent":{"xt":"urn:btih:fa1589fbbda8880bd05dfd262f6e1cc53f390b28","amp;dn":"TeenSexMovs.-.Berta.Aka.Grace","amp;tr":["udp%3A%2F%2Ftracker.openbittorrent.com%3A80","udp%3A%2F%2Fopen.demonii.com%3A1337","udp%3A%2F%2Ftracker.coppersurfer.tk%3A6969","udp%3A%2F%2Fexodus.desync.com%3A6969"],"infoHash":"fa1589fbbda8880bd05dfd262f6e1cc53f390b28","infoHashBuffer":{"type":"Buffer","data":[250,21,137,251,189,168,136,11,208,93,253,38,47,110,28,197,63,57,11,40]},"announce":[],"urlList":[]}}