{"title":"Maplesoft.Maple.v14.0-TBE","uid":5824806,"size":393507431,"categoryP":"applications","categoryS":"windows","magnet":"?xt=urn:btih:fe6b682c26e9f3bc52c2abf548bb70a5087113e4&amp;dn=Maplesoft.Maple.v14.0-TBE&amp;tr=udp%3A%2F%2Ftracker.openbittorrent.com%3A80&amp;tr=udp%3A%2F%2Fopen.demonii.com%3A1337&amp;tr=udp%3A%2F%2Ftracker.coppersurfer.tk%3A6969&amp;tr=udp%3A%2F%2Fexodus.desync.com%3A6969","seeders":0,"leechers":0,"uploader":"MAFIAA.","files":81,"time":1284216197,"description":"DATE......: 10-09-2010      SUPPLiER...: TEAM TBE\nTYPE......: Application      PACKAGER...: TEAM TBE\nOS........: WinAll          CRACKER....: TEAM TBE\nDisks.....: XX/79          PROTECTION.: FlexLM\n\n..: RELEASE NOTES :..\n\nMaple is the essential technical computing software for todays\nengineers, mathematicians, and scientists. Whether you need to do\nquick calculations, develop design sheets, teach fundamental\nconcepts, or produce sophisticated high-fidelity simulation models,\nMaples world-leading computation engine offers the breadth, depth,\nand performance to handle every type of mathematics.\n\nURL &lt;a href=&quot;\nhttp://www.maplesoft.com/&quot; rel=&quot;nofollow&quot; target=&quot;_NEW&quot;&gt;\nhttp://www.maplesoft.com/&lt;/a&gt;\n\n\n..: iNSTALL NOTES :..\n\n1.) install\n2.) use single-user licensing\n3.) choose activate later\n4.) copy lic to installdirlicense","torrent":{"xt":"urn:btih:fe6b682c26e9f3bc52c2abf548bb70a5087113e4","amp;dn":"Maplesoft.Maple.v14.0-TBE","amp;tr":["udp%3A%2F%2Ftracker.openbittorrent.com%3A80","udp%3A%2F%2Fopen.demonii.com%3A1337","udp%3A%2F%2Ftracker.coppersurfer.tk%3A6969","udp%3A%2F%2Fexodus.desync.com%3A6969"],"infoHash":"fe6b682c26e9f3bc52c2abf548bb70a5087113e4","infoHashBuffer":{"type":"Buffer","data":[254,107,104,44,38,233,243,188,82,194,171,245,72,187,112,165,8,113,19,228]},"announce":[],"urlList":[]}}